is_even/__init__.py
is_even/is_even.py
iseven_lucasedng-0.0.7.dist-info/LICENSE
iseven_lucasedng-0.0.7.dist-info/METADATA
iseven_lucasedng-0.0.7.dist-info/WHEEL
iseven_lucasedng-0.0.7.dist-info/top_level.txt
iseven_lucasedng-0.0.7.dist-info/RECORD
