Metadata-Version: 2.1
Name: iseven-lucasedng
Version: 0.0.7
Summary: A smart way to find out if a number is even
Home-page: UNKNOWN
Author: lucasedng (Lucas Gonçalves)
Author-email: lucasedng@gmail.com
License: UNKNOWN
Keywords: python,number,even
Platform: UNKNOWN
Classifier: Development Status :: 1 - Planning
Classifier: Intended Audience :: Developers
Classifier: Programming Language :: Python :: 3
Classifier: Operating System :: Unix
Classifier: Operating System :: MacOS :: MacOS X
Classifier: Operating System :: Microsoft :: Windows
License-File: LICENSE
